tegda/__init__.py
tegda/cli.py
tegda/tegda.py
tegda/utils.py
tegda-0.1.4.2.dist-info/AUTHORS.rst
tegda-0.1.4.2.dist-info/LICENSE
tegda-0.1.4.2.dist-info/METADATA
tegda-0.1.4.2.dist-info/WHEEL
tegda-0.1.4.2.dist-info/entry_points.txt
tegda-0.1.4.2.dist-info/top_level.txt
tegda-0.1.4.2.dist-info/RECORD
