Metadata-Version: 2.1
Name: tegda
Version: 0.1.4.2
Summary: Tegda creates customizable visual representations of data for exploratory analysis.
Home-page: https://github.com/Robertoarce/tegda
Author: Roberto Arce Aguirre
Author-email: roberto_arce_@hotmail.com
License: MIT license
Keywords: tegda
Platform: UNKNOWN
Classifier: Development Status :: 2 - Pre-Alpha
Classifier: Intended Audience :: Developers
Classifier: License :: OSI Approved :: MIT License
Classifier: Natural Language :: English
Classifier: Programming Language :: Python :: 3
Classifier: Programming Language :: Python :: 3.6
Classifier: Programming Language :: Python :: 3.7
Classifier: Programming Language :: Python :: 3.8
Requires-Python: >=3.6
Requires-Dist: Click (>=7.0)
